fintie/__init__.py
fintie/__main__.py
fintie/__version__.py
fintie/cli.py
fintie/config.py
fintie/env.py
fintie/stock/__init__.py
fintie/stock/announcement.py
fintie/stock/cli.py
fintie/stock/fenhong.py
fintie/stock/fundamentals.py
fintie/stock/fundamentals_xq.py
fintie/stock/guben.py
fintie/stock/gudong.py
fintie/stock/hist_quotes.py
fintie/stock/insider.py
fintie/stock/list_quotes.py
fintie/stock/live_quotes.py
fintie/stock/mkt_calendar.py
fintie/stock/picker_xq.py
fintie/stock/utils.py
fintie/stock/zengfa.py
fintie/utils/__init__.py
fintie-0.1.3.dist-info/DESCRIPTION.rst
fintie-0.1.3.dist-info/LICENSE.txt
fintie-0.1.3.dist-info/METADATA
fintie-0.1.3.dist-info/RECORD
fintie-0.1.3.dist-info/WHEEL
fintie-0.1.3.dist-info/entry_points.txt
fintie-0.1.3.dist-info/metadata.json
fintie-0.1.3.dist-info/top_level.txt
fintie-0.1.3.dist-info/zip-safe
