Metadata-Version: 2.0
Name: fintie
Version: 0.1.3
Summary: a common data obtain tool
Home-page: https://github.com/qytz/fintie
Author: qytz
Author-email: hhhhhf@foxmail.com
License: Apache License 2.0
Keywords: fintie
Platform: UNKNOWN
Classifier: Framework :: Robot Framework
Classifier: Development Status :: 3 - Alpha
Classifier: Intended Audience :: Developers
Classifier: Operating System :: POSIX :: Linux
Classifier: License :: OSI Approved :: Apache Software License
Classifier: Natural Language :: Chinese (Simplified)
Classifier: Programming Language :: Python :: 3 :: Only
Classifier: Programming Language :: Python :: 3.6
Requires-Python: >=3.6*
Requires-Dist: aiohttp
Requires-Dist: click
Requires-Dist: pandas
Requires-Dist: pytest
Requires-Dist: python-dateutil
Requires-Dist: sqlalchemy
